setup.py
busybox/__init__.py
busybox/color_slowprint.py
busybox/slowprint.py
ljf7_busybox.egg-info/PKG-INFO
ljf7_busybox.egg-info/SOURCES.txt
ljf7_busybox.egg-info/dependency_links.txt
ljf7_busybox.egg-info/top_level.txt