Metadata-Version: 2.1
Name: ljf7-busybox
Version: 1.2.1
Summary: Colorful and slow print
Author: Andy Woz
Author-email: chatgptt898@gmail.com
